tdtools/__init__.py
tdtools/dbc.json
tdtools/dbtree.py
tdtools/helpstats.py
tdtools/priv.json
tdtools/tbtree.py
tdtools/tdexpl.py
tdtools/tdrights.py
tdtools/tptexp.py
tdtools/tptload.py
tdtools/updviewrefs.py
tdtools/util.py
tdtools/vsch.py
tdtools/ls/__init__.py
tdtools/ls/db.py
tdtools/ls/prof.py
tdtools/ls/rmem.py
tdtools/ls/role.py
tdtools/ls/tvm.py
tdtools/ls/user.py
tdtools/ls/util.py
tdtools/ls/view.py
tdtools/show/__init__.py
tdtools/show/db.py
tdtools/show/grant.py
tdtools/show/prof.py
tdtools/show/role.py
tdtools/show/stats.py
tdtools/show/tvm.py
tdtools/show/util.py
tdtools/show/zone.py
tdtools-0.8.1.dist-info/METADATA
tdtools-0.8.1.dist-info/WHEEL
tdtools-0.8.1.dist-info/entry_points.txt
tdtools-0.8.1.dist-info/top_level.txt
tdtools-0.8.1.dist-info/RECORD
