Metadata-Version: 2.1
Name: tdtools
Version: 0.8.1
Summary: A Collection of assorted Teradata Tools
Home-page: https://bitbucket.org/padhia/tdtools
Author: Paresh Adhia
License: GPL
Keywords: teradata
Platform: UNKNOWN
Classifier: Development Status :: 4 - Beta
Classifier: License :: OSI Approved :: GNU General Public License (GPL)
Classifier: Intended Audience :: Developers
Classifier: Intended Audience :: System Administrators
Classifier: Intended Audience :: End Users/Desktop
Classifier: Topic :: Database
Classifier: Topic :: Utilities
Classifier: Programming Language :: Python :: 3 :: Only
Classifier: Programming Language :: Python :: 3.7
Classifier: Programming Language :: Python :: 3.8
Requires-Python: >=3.7
Requires-Dist: tdtypes (>=0.5.1)
Requires-Dist: yappt
Requires-Dist: cached-property
